pyscada/__init__.py
pyscada/admin.py
pyscada/apps.py
pyscada/device.py
pyscada/models.py
pyscada/signals.py
pyscada/tests.py
pyscada/views.py
pyscada/core/__init__.py
pyscada/event/__init__.py
pyscada/event/worker.py
pyscada/export/__init__.py
pyscada/export/admin.py
pyscada/export/apps.py
pyscada/export/csv_file.py
pyscada/export/export.py
pyscada/export/hdf5_file.py
pyscada/export/models.py
pyscada/export/worker.py
pyscada/export/management/__init__.py
pyscada/export/management/commands/PyScadaExportData.py
pyscada/export/management/commands/__init__.py
pyscada/export/migrations/0001_initial.py
pyscada/export/migrations/0002_auto_20151201_1617.py
pyscada/export/migrations/0003_auto_20160315_1140.py
pyscada/export/migrations/0004_exporttask.py
pyscada/export/migrations/0005_auto_20160403_1454.py
pyscada/export/migrations/0006_auto_20160404_0949.py
pyscada/export/migrations/0007_auto_20161124_1002.py
pyscada/export/migrations/0008_auto_20161124_1003.py
pyscada/export/migrations/0009_auto_20161128_0948.py
pyscada/export/migrations/0010_auto_20161128_1049.py
pyscada/export/migrations/0011_exporttask_filename.py
pyscada/export/migrations/0012_exporttask_backgroundprocess.py
pyscada/export/migrations/0013_auto_20170711_0729.py
pyscada/export/migrations/0014_auto_20170711_1326.py
pyscada/export/migrations/0015_remove_exporttask_backgroundtask.py
pyscada/export/migrations/0016_auto_20191004_0912.py
pyscada/export/migrations/__init__.py
pyscada/fixtures/color.json
pyscada/fixtures/units.json
pyscada/generic/__init__.py
pyscada/generic/device.py
pyscada/generic/worker.py
pyscada/generic/devices/__init__.py
pyscada/generic/devices/dummy.py
pyscada/generic/devices/waveform.py
pyscada/hmi/__init__.py
pyscada/hmi/admin.py
pyscada/hmi/apps.py
pyscada/hmi/models.py
pyscada/hmi/signals.py
pyscada/hmi/urls.py
pyscada/hmi/views.py
pyscada/hmi/migrations/0001_initial.py
pyscada/hmi/migrations/0002_auto_20151016_1932.py
pyscada/hmi/migrations/0003_auto_20151130_1456.py
PyScada-0.8.0.dist-info/AUTHORS
PyScada-0.8.0.dist-info/LICENSE
PyScada-0.8.0.dist-info/METADATA
PyScada-0.8.0.dist-info/WHEEL
PyScada-0.8.0.dist-info/top_level.txt
PyScada-0.8.0.dist-info/RECORD
